02_outlab/task6/tick_gen.v
// A free-running tick generator. In real hardware LIMIT would be set so that
// tick pulses once per second (e.g. LIMIT = your clock frequency in Hz).
// For simulation we use a small LIMIT so you don't have to wait for millions
// of clock edges to see the stopwatch actually move.
//
// This module is complete -- you do not need to modify it, just instantiate
// it inside stopwatch.v.

module tick_gen #(
    parameter LIMIT = 4
) (
    input  wire clk,
    input  wire rst,
    output reg  tick
);
    reg [31:0] counter;

    always @(posedge clk) begin
        if (rst) begin
            counter <= 32'd0;
            tick    <= 1'b0;
        end else if (counter == LIMIT - 1) begin
            counter <= 32'd0;
            tick    <= 1'b1;
        end else begin
            counter <= counter + 32'd1;
            tick    <= 1'b0;
        end
    end
endmodule

02_outlab/task6/stopwatch.v
// TODO: 2-3 sentence written justification goes here.
// Why is `running` a reg? Why is the carry out of sec_ones naturally a
// wire, even though it's computed from values that are themselves regs?
//'running' is a reg cause we have to invert it as posedge of start_stop(just need a toggle) which we couldn't do by making it a wire
// carry carrriers are wires because the actually depend on current values of parameters only and dont need any storing memory.
module stopwatch (
    input  wire clk,
    input  wire rst,
    input  wire start_stop,   // one clock-cycle pulse per "button press"
    output reg [3:0] sec_ones,
    output reg [3:0] sec_tens,
    output reg [3:0] min_ones,
    output reg [3:0] min_tens,
    output wire tick_out       // exposes tick_gen's tick for the testbench;
                                // a real stopwatch chip wouldn't need this pin
);
    // Instantiate tick_gen here. Use a small LIMIT (e.g. 4) so the
    // testbench doesn't have to wait forever. Connect its tick output to
    // both your internal logic and to tick_out above.
    tick_gen tt(.clk(clk),.rst(rst),.tick(tick));
    assign tick_out=tick;
    // running: a reg that toggles every time start_stop pulses high.
    // This is the only piece of state that decides whether anything
    // else in this module is allowed to change.
    reg running;
    initial begin
        running<=1'b0;
    end
    always @(posedge start_stop ) begin
        running<=running^start_stop;
    end
    // Combinational logic: for each digit, decide (a) whether it should
    // roll over back to 0 this tick, and (b) whether it should carry
    // into the next digit. sec_ones rolls over at 10 (0-9) and carries
    // into sec_tens; sec_tens rolls over at 6 (seconds only go 0-59) and
    // carries into min_ones; min_ones rolls over at 10 and carries into
    // min_tens; min_tens rolls over at 6, wrapping the whole stopwatch
    // back to 00:00.
    wire [2:0] carry;
    assign carry[0]=(sec_ones==4'b1001);
    assign carry[1]=carry[0]&&(sec_tens==4'b0101);
    assign carry[2]=carry[1]&&(min_ones==4'b1001);
    wire [3:0] digit [3:0];
    assign digit[0]=carry[0]?4'b0000:(sec_ones+4'b1);
    assign digit[1]=carry[1]?4'b0000:(sec_tens+carry[0]);
    assign digit[2]=carry[2]?4'b0000:(min_ones+carry[1]);
    assign digit[3]=(min_tens==4'b0101&&carry[2])?4'b0000:(min_tens+carry[2]);
    

    //
    // Sequential logic: on posedge clk, if rst is high, zero everything.
    // Otherwise, if running and tick, apply the next values you computed
    // combinationally above. If not running, or no tick this cycle, hold.
    always @(posedge clk ) begin
        if(rst) begin
            sec_ones<=4'b0000;
            sec_tens<=4'b0000;
            min_ones<=4'b0000;
            min_tens<=4'b0000;
        end
        else if(running&&tick) begin
            sec_ones<=digit[0];
            sec_tens<=digit[1];
            min_ones<=digit[2];
            min_tens<=digit[3];
    end
    end
endmodule

02_outlab/task6/tb_task6.v
`timescale 1ns/1ns

module tb;
    reg clk, rst, start_stop;
    wire [3:0] sec_ones, sec_tens, min_ones, min_tens;
    wire tick_out;
    integer errors;

    stopwatch uut (
        .clk(clk),
        .rst(rst),
        .start_stop(start_stop),
        .sec_ones(sec_ones),
        .sec_tens(sec_tens),
        .min_ones(min_ones),
        .min_tens(min_tens),
        .tick_out(tick_out)
    );

    always #5 clk = ~clk;

    initial begin
        $monitor("At time %0t: %0d%0d:%0d%0d",
                  $time, min_tens, min_ones, sec_tens, sec_ones);
    end

    // Safety net: if tick_out is never driven (e.g. tick_gen wasn't
    // instantiated/wired up yet), wait_ticks would otherwise wait forever.
    initial begin
        #2000;
        $display("TIMEOUT: tick_out never toggled -- did you instantiate");
        $display("tick_gen and connect its tick output to tick_out?");
        $finish;
    end

    task press_start_stop;
        begin
            @(posedge clk);
            #1 start_stop = 1'b1;
            @(posedge clk);
            #1 start_stop = 1'b0;
        end
    endtask

    // Wait for n actual tick pulses from the tick generator, then one more
    // clock edge for the registered digit update in response to the last
    // tick to land.
    task wait_ticks(input integer n);
        integer i;
        begin
            for (i = 0; i < n; i = i + 1)
                @(posedge tick_out);
            @(posedge clk);
        end
    endtask

    task check(
        input [3:0] exp_mt, input [3:0] exp_mo,
        input [3:0] exp_st, input [3:0] exp_so
    );
        begin
            #1;
            if (min_tens !== exp_mt || min_ones !== exp_mo ||
                sec_tens !== exp_st || sec_ones !== exp_so) begin
                errors = errors + 1;
                $display("  WRONG: expected %0d%0d:%0d%0d, got %0d%0d:%0d%0d",
                          exp_mt, exp_mo, exp_st, exp_so,
                          min_tens, min_ones, sec_tens, sec_ones);
            end
        end
    endtask

    initial begin
        errors = 0;
        clk = 0; rst = 1; start_stop = 0;
        $dumpfile("task6.vcd");
        $dumpvars(0, tb);

        #10;
        check(0, 0, 0, 0);

        // still not running: time should not advance even after many ticks
        rst = 0;
        repeat (20) @(posedge clk);
        check(0, 0, 0, 0);

        // start the stopwatch, let 3 ticks pass
        press_start_stop;
        wait_ticks(3);
        check(0, 0, 0, 3);

        // stop it, confirm it holds even as more ticks would have occurred
        press_start_stop;
        repeat (16) @(posedge clk);
        check(0, 0, 0, 3);

        // resume
        press_start_stop;

        // backdoor-load digits close to a rollover boundary to test carry
        // logic without simulating thousands of cycles from zero
        @(negedge clk);
        uut.sec_ones = 4'd9;
        uut.sec_tens = 4'd5;
        uut.min_ones = 4'd0;
        uut.min_tens = 4'd0;

        // one tick: seconds should roll 59 -> 00 and carry into minutes
        wait_ticks(1);
        check(0, 1, 0, 0);

        // load right up against a full wraparound: 59:59 -> 00:00
        @(negedge clk);
        uut.sec_ones = 4'd9;
        uut.sec_tens = 4'd5;
        uut.min_ones = 4'd9;
        uut.min_tens = 4'd5;

        wait_ticks(1);
        check(0, 0, 0, 0);

        // reset should zero everything immediately regardless of running state
        rst = 1;
        @(posedge clk);
        check(0, 0, 0, 0);

        if (errors == 0)
            $display("PASS: stopwatch behaves correctly.");
        else
            $display("FAIL: %0d mismatch(es) found.", errors);

        $finish;
    end
endmodule

02_outlab/task6.vcd
$date
	Tue Aug 18 18:58:22 2026
$end
$version
	Icarus Verilog
$end
$timescale
	1ns
$end
$scope module tb $end
$var wire 1 ! tick_out $end
$var wire 4 " sec_tens [3:0] $end
$var wire 4 # sec_ones [3:0] $end
$var wire 4 $ min_tens [3:0] $end
$var wire 4 % min_ones [3:0] $end
$var reg 1 & clk $end
$var reg 1 ' rst $end
$var reg 1 ( start_stop $end
$var integer 32 ) errors [31:0] $end
$scope module uut $end
$var wire 1 & clk $end
$var wire 1 ' rst $end
$var wire 1 ( start_stop $end
$var wire 1 ! tick_out $end
$var wire 1 * tick $end
$var wire 3 + carry [2:0] $end
$var reg 4 , min_ones [3:0] $end
$var reg 4 - min_tens [3:0] $end
$var reg 1 . running $end
$var reg 4 / sec_ones [3:0] $end
$var reg 4 0 sec_tens [3:0] $end
$scope module tt $end
$var wire 1 & clk $end
$var wire 1 ' rst $end
$var parameter 32 1 LIMIT $end
$var reg 32 2 counter [31:0] $end
$var reg 1 * tick $end
$upscope $end
$upscope $end
$scope task check $end
$var reg 4 3 exp_mo [3:0] $end
$var reg 4 4 exp_mt [3:0] $end
$var reg 4 5 exp_so [3:0] $end
$var reg 4 6 exp_st [3:0] $end
$upscope $end
$scope task press_start_stop $end
$upscope $end
$scope task wait_ticks $end
$var integer 32 7 i [31:0] $end
$var integer 32 8 n [31:0] $end
$upscope $end
$upscope $end
$enddefinitions $end
$comment Show the parameter values. $end
$dumpall
b100 1
$end
#0
$dumpvars
bx 8
bx 7
bx 6
bx 5
bx 4
bx 3
bx 2
bx 0
bx /
0.
bx -
bx ,
bx +
x*
b0 )
0(
1'
0&
bx %
bx $
bx #
bx "
x!
$end
#5
0!
0*
b0 2
b0 $
b0 -
b0 %
b0 ,
b0 "
b0 0
b0 +
b0 #
b0 /
1&
#10
0&
b0 5
b0 6
b0 3
b0 4
#11
0'
#15
b1 2
1&
#20
0&
#25
b10 2
1&
#30
0&
#35
b11 2
1&
#40
0&
#45
1!
1*
b0 2
1&
#50
0&
#55
0!
0*
b1 2
1&
#60
0&
#65
b10 2
1&
#70
0&
#75
b11 2
1&
#80
0&
#85
1!
1*
b0 2
1&
#90
0&
#95
0!
0*
b1 2
1&
#100
0&
#105
b10 2
1&
#110
0&
#115
b11 2
1&
#120
0&
#125
1!
1*
b0 2
1&
#130
0&
#135
0!
0*
b1 2
1&
#140
0&
#145
b10 2
1&
#150
0&
#155
b11 2
1&
#160
0&
#165
1!
1*
b0 2
1&
#170
0&
#175
0!
0*
b1 2
1&
#180
0&
#185
b10 2
1&
#190
0&
#195
b11 2
1&
#200
0&
#205
1!
1*
b0 2
1&
#210
0&
#215
0!
0*
b1 2
1&
#216
1.
1(
#220
0&
#225
b10 2
1&
#226
b0 7
b11 8
0(
#230
0&
#235
b11 2
1&
#240
0&
#245
b1 7
1!
1*
b0 2
1&
#250
0&
#255
b1 #
b1 /
0!
0*
b1 2
1&
#260
0&
#265
b10 2
1&
#270
0&
#275
b11 2
1&
#280
0&
#285
b10 7
1!
1*
b0 2
1&
#290
0&
#295
b10 #
b10 /
0!
0*
b1 2
1&
#300
0&
#305
b10 2
1&
#310
0&
#315
b11 2
1&
#320
0&
#325
b11 7
1!
1*
b0 2
1&
#330
0&
#335
b11 #
b11 /
0!
0*
b1 2
b11 5
1&
#340
0&
#345
b10 2
1&
#346
0.
1(
#350
0&
#355
b11 2
1&
#356
0(
#360
0&
#365
1!
1*
b0 2
1&
#370
0&
#375
0!
0*
b1 2
1&
#380
0&
#385
b10 2
1&
#390
0&
#395
b11 2
1&
#400
0&
#405
1!
1*
b0 2
1&
#410
0&
#415
0!
0*
b1 2
1&
#420
0&
#425
b10 2
1&
#430
0&
#435
b11 2
1&
#440
0&
#445
1!
1*
b0 2
1&
#450
0&
#455
0!
0*
b1 2
1&
#460
0&
#465
b10 2
1&
#470
0&
#475
b11 2
1&
#480
0&
#485
1!
1*
b0 2
1&
#490
0&
#495
0!
0*
b1 2
1&
#500
0&
#505
b10 2
1&
#510
0&
#515
b11 2
1&
#520
0&
#525
1!
1*
b0 2
1&
#526
1.
1(
#530
0&
#535
b100 #
b100 /
0!
0*
b1 2
1&
#536
0(
#540
b0 7
b1 8
b101 "
b101 0
b11 +
b1001 #
b1001 /
0&
#545
b10 2
1&
#550
0&
#555
b11 2
1&
#560
0&
#565
b1 7
1!
1*
b0 2
1&
#570
0&
#575
b1 %
b1 ,
b0 "
b0 0
b0 +
b0 #
b0 /
0!
0*
b1 2
b0 5
b1 3
1&
#580
b0 7
b101 $
b101 -
b1001 %
b1001 ,
b101 "
b101 0
b111 +
b1001 #
b1001 /
0&
#585
b10 2
1&
#590
0&
#595
b11 2
1&
#600
0&
#605
b1 7
1!
1*
b0 2
1&
#610
0&
#615
b0 $
b0 -
b0 %
b0 ,
b0 "
b0 0
b0 +
b0 #
b0 /
0!
0*
b1 2
b0 3
1&
#616
1'
#620
0&
#625
b0 2
1&
