02_outlab/task5/sat_counter.v
module sat_counter (
    input wire clk,
    input wire rst,
    input wire up,
    input wire down,
    output reg [3:0] count
);
    // Design this module yourself, following the pattern from Task 3/4:
    // a combinational block (a wire) computes the next value of count,
    // and a sequential block registers it on the clock edge.
    //
    // Behavior:
    //   - synchronous rst forces count to 0, overriding everything else
    //   - if up=1 and down=0: count increments, but saturates at 15 (stays
    //     at 15 instead of wrapping to 0)
    //   - if down=1 and up=0: count decrements, but saturates at 0 (stays
    //     at 0 instead of wrapping to 15)
    //   - if up and down are equal (00 or 11): count holds its value
    wire [3:0] expected;
    wire [3:0] num;
    wire[3:0] sum;
    assign expected[0]=(up^down) ? 1:0;
    assign expected[3:1]=3'b000;
    assign num[3:0]=down? expected[3:0]^4'b1111:expected[3:0];
    assign sum= count+((down&&count!=4'b0000) ? (num+4'b0001):((up&&count!=4'b1111) ? num:4'b0000));
    always @(posedge clk ) begin
        if(rst) begin
            count<=4'b0000;
        end
        else begin
            count<=sum;
        end
    end


endmodule

02_outlab/task5/tb_task5.v
`timescale 1ns/1ns

module tb;
    reg clk, rst, up, down;
    wire [3:0] count;
    integer i;
    integer errors;

    sat_counter uut (
        .clk(clk),
        .rst(rst),
        .up(up),
        .down(down),
        .count(count)
    );

    always #5 clk = ~clk;

    initial begin
        $monitor("At time %0t: rst=%b up=%b down=%b -> count=%0d",
                  $time, rst, up, down, count);
    end

    task check(input [3:0] expected);
        begin
            #1;
            if (count !== expected) begin
                errors = errors + 1;
                $display("  WRONG: expected %0d, got %0d", expected, count);
            end
        end
    endtask

    initial begin
        errors = 0;
        clk = 0; rst = 1; up = 0; down = 0;
        $dumpfile("task5.vcd");
        $dumpvars(0, tb);

        #10 check(0);
        rst = 0;

        // count up to saturation at 15
        up = 1; down = 0;
        for (i = 0; i < 20; i = i + 1) begin
            #10;
        end
        check(15);

        // hold when up == down
        up = 1; down = 1; #10; check(15);
        up = 0; down = 0; #10; check(15);

        // count down to saturation at 0
        up = 0; down = 1;
        for (i = 0; i < 20; i = i + 1) begin
            #10;
        end
        check(0);

        // a few ordinary steps
        up = 1; down = 0; #10; check(1);
        up = 1; down = 0; #10; check(2);
        down = 1; up = 0; #10; check(1);

        // reset overrides everything
        rst = 1; up = 1; down = 0; #10; check(0);

        if (errors == 0)
            $display("PASS: sat_counter behaves correctly.");
        else
            $display("FAIL: %0d mismatch(es) found.", errors);

        $finish;
    end
endmodule

02_outlab/task5.vcd
$date
	Tue Aug 18 17:46:44 2026
$end
$version
	Icarus Verilog
$end
$timescale
	1ns
$end
$scope module tb $end
$var wire 4 ! count [3:0] $end
$var reg 1 " clk $end
$var reg 1 # down $end
$var reg 1 $ rst $end
$var reg 1 % up $end
$var integer 32 & errors [31:0] $end
$var integer 32 ' i [31:0] $end
$scope module uut $end
$var wire 1 " clk $end
$var wire 1 # down $end
$var wire 1 $ rst $end
$var wire 1 % up $end
$var wire 4 ( sum [3:0] $end
$var wire 4 ) num [3:0] $end
$var wire 4 * expected [3:0] $end
$var reg 4 + count [3:0] $end
$upscope $end
$scope task check $end
$var reg 4 , expected [3:0] $end
$upscope $end
$upscope $end
$enddefinitions $end
$comment Show the parameter values. $end
$dumpall
$end
#0
$dumpvars
bx ,
bx +
b0 *
b0 )
bx (
bx '
b0 &
0%
1$
0#
0"
bx !
$end
#5
b0 (
b0 !
b0 +
1"
#10
0"
b0 ,
#11
b1 (
b1 )
b1 *
b0 '
1%
0$
#15
b10 (
b1 !
b1 +
1"
#20
0"
#21
b1 '
#25
b11 (
b10 !
b10 +
1"
#30
0"
#31
b10 '
#35
b100 (
b11 !
b11 +
1"
#40
0"
#41
b11 '
#45
b101 (
b100 !
b100 +
1"
#50
0"
#51
b100 '
#55
b110 (
b101 !
b101 +
1"
#60
0"
#61
b101 '
#65
b111 (
b110 !
b110 +
1"
#70
0"
#71
b110 '
#75
b1000 (
b111 !
b111 +
1"
#80
0"
#81
b111 '
#85
b1001 (
b1000 !
b1000 +
1"
#90
0"
#91
b1000 '
#95
b1010 (
b1001 !
b1001 +
1"
#100
0"
#101
b1001 '
#105
b1011 (
b1010 !
b1010 +
1"
#110
0"
#111
b1010 '
#115
b1100 (
b1011 !
b1011 +
1"
#120
0"
#121
b1011 '
#125
b1101 (
b1100 !
b1100 +
1"
#130
0"
#131
b1100 '
#135
b1110 (
b1101 !
b1101 +
1"
#140
0"
#141
b1101 '
#145
b1111 (
b1110 !
b1110 +
1"
#150
0"
#151
b1110 '
#155
b1111 (
b1111 !
b1111 +
1"
#160
0"
#161
b1111 '
#165
1"
#170
0"
#171
b10000 '
#175
1"
#180
0"
#181
b10001 '
#185
1"
#190
0"
#191
b10010 '
#195
1"
#200
0"
#201
b10011 '
#205
1"
#210
0"
#211
b1111 ,
b10100 '
#212
b0 *
b1111 (
b1111 )
1#
#215
1"
#220
0"
#223
b0 )
0#
0%
#225
1"
#230
0"
#234
b1110 (
b1 *
b1110 )
b0 '
1#
#235
b1101 (
b1110 !
b1110 +
1"
#240
0"
#244
b1 '
#245
b1100 (
b1101 !
b1101 +
1"
#250
0"
#254
b10 '
#255
b1011 (
b1100 !
b1100 +
1"
#260
0"
#264
b11 '
#265
b1010 (
b1011 !
b1011 +
1"
#270
0"
#274
b100 '
#275
b1001 (
b1010 !
b1010 +
1"
#280
0"
#284
b101 '
#285
b1000 (
b1001 !
b1001 +
1"
#290
0"
#294
b110 '
#295
b111 (
b1000 !
b1000 +
1"
#300
0"
#304
b111 '
#305
b110 (
b111 !
b111 +
1"
#310
0"
#314
b1000 '
#315
b101 (
b110 !
b110 +
1"
#320
0"
#324
b1001 '
#325
b100 (
b101 !
b101 +
1"
#330
0"
#334
b1010 '
#335
b11 (
b100 !
b100 +
1"
#340
0"
#344
b1011 '
#345
b10 (
b11 !
b11 +
1"
#350
0"
#354
b1100 '
#355
b1 (
b10 !
b10 +
1"
#360
0"
#364
b1101 '
#365
b0 (
b1 !
b1 +
1"
#370
0"
#374
b1110 '
#375
b0 (
b0 !
b0 +
1"
#380
0"
#384
b1111 '
#385
1"
#390
0"
#394
b10000 '
#395
1"
#400
0"
#404
b10001 '
#405
1"
#410
0"
#414
b10010 '
#415
1"
#420
0"
#424
b10011 '
#425
1"
#430
0"
#434
b0 ,
b10100 '
#435
b1 (
b1 )
0#
1%
1"
#440
0"
#445
b10 (
b1 !
b1 +
1"
b1 ,
#450
0"
#455
b11 (
b10 !
b10 +
1"
#456
b10 ,
#457
b1 (
b1110 )
0%
1#
#460
0"
#465
b0 (
b1 !
b1 +
1"
#467
b1 ,
#468
b10 (
b1 )
0#
1%
1$
#470
0"
#475
b1 (
b0 !
b0 +
1"
#478
b0 ,
