02_outlab/task2/mux_behavioral.v
module mux_behavioral (
    input wire a,
    input wire b,
    input wire sel,
    output reg y
);
always @(*) begin
    if(sel==1'b0) begin
        y<=a;
    end
    else begin
        y<=b;
    end
end
endmodule

02_outlab/task3/loadable_reg.v
module loadable_reg (
    input wire clk,
    input wire rst,
    input wire load,
    input wire d,
    output reg q
);
    mux_behavioral uut(.a(q),.b(d),.sel(load),.y(q_t1));
    always @(posedge clk) begin
        if(rst==1'b1) begin
            q=1'b0;
        end
        else begin
            q<=q_t1;
        end
    end
    // Hint: instantiate mux_behavioral to compute the next value of q
    // (hold q if load is low, take d if load is high), then register
    // that value on the clock edge.

endmodule

02_outlab/task3/tb_task3.v
`timescale 1ns/1ns

module tb;
    reg clk, rst, load, d;
    wire q;

    loadable_reg uut (
        .clk(clk),
        .rst(rst),
        .load(load),
        .d(d),
        .q(q)
    );

    always #5 clk = ~clk;

    initial begin
        $monitor("At time %0t: rst = %b, load = %b, d = %b -> q = %b",
                  $time, rst, load, d, q);
    end

    initial begin
        clk = 0; rst = 1; load = 0; d = 0;
        $dumpfile("task3.vcd");
        $dumpvars(0, tb);

        #10 rst = 0;

        // q should hold at 0 while load is low, regardless of d
        d = 1; load = 0; #10;
        d = 1; load = 0; #10;

        // q should load d on the next clock edge
        d = 1; load = 1; #10;
        load = 0; #10;

        // q should keep holding its last loaded value
        d = 0; load = 0; #10;

        // load a new value
        d = 0; load = 1; #10;
        load = 0; #10;

        // synchronous reset should override everything
        d = 1; load = 1; rst = 1; #10;

        $finish;
    end
endmodule

02_outlab/task3.vcd
$date
	Mon Aug 17 09:42:49 2026
$end
$version
	Icarus Verilog
$end
$timescale
	1ns
$end
$scope module tb $end
$var wire 1 ! q $end
$var reg 1 " clk $end
$var reg 1 # d $end
$var reg 1 $ load $end
$var reg 1 % rst $end
$scope module uut $end
$var wire 1 " clk $end
$var wire 1 # d $end
$var wire 1 $ load $end
$var wire 1 % rst $end
$var wire 1 & q_t1 $end
$var reg 1 ! q $end
$scope module uut $end
$var wire 1 ! a $end
$var wire 1 # b $end
$var wire 1 $ sel $end
$var reg 1 & y $end
$upscope $end
$upscope $end
$upscope $end
$enddefinitions $end
$comment Show the parameter values. $end
$dumpall
$end
#0
$dumpvars
x&
1%
0$
0#
0"
x!
$end
#5
0&
0!
1"
#10
0"
1#
0%
#15
1"
#20
0"
#25
1"
#30
1&
0"
1$
#35
1!
1"
#40
0"
0$
#45
1"
#50
0"
0#
#55
1"
#60
0&
0"
1$
#65
0!
1"
#70
0"
0$
#75
1"
#80
1&
0"
1%
1$
1#
